gabrieltool/__init__.py
gabrieltool/statemachine/__init__.py
gabrieltool/statemachine/fsm.py
gabrieltool/statemachine/instruction_pb2.py
gabrieltool/statemachine/runner.py
gabrieltool/statemachine/wca_state_machine_pb2.py
gabrieltool/statemachine/callable_zoo/__init__.py
gabrieltool/statemachine/callable_zoo/base.py
gabrieltool/statemachine/callable_zoo/predicate_zoo/__init__.py
gabrieltool/statemachine/callable_zoo/predicate_zoo/base.py
gabrieltool/statemachine/callable_zoo/processor_zoo/__init__.py
gabrieltool/statemachine/callable_zoo/processor_zoo/base.py
gabrieltool/statemachine/callable_zoo/processor_zoo/containerized.py
gabrieltool/statemachine/callable_zoo/processor_zoo/tfutils.py
gabrieltool-1.1.1.data/scripts/gbt
gabrieltool-1.1.1.dist-info/AUTHORS.rst
gabrieltool-1.1.1.dist-info/LICENSE
gabrieltool-1.1.1.dist-info/METADATA
gabrieltool-1.1.1.dist-info/WHEEL
gabrieltool-1.1.1.dist-info/top_level.txt
gabrieltool-1.1.1.dist-info/RECORD
