Metadata-Version: 2.1
Name: gabrieltool
Version: 1.1.1
Summary: Tools for Making Wearable Cognitive Assitants
Home-page: https://github.com/junjuew/gabriel-tool
Author: Junjue Wang
Author-email: junjuew@cs.cmu.edu
License: Apache Software License 2.0
Keywords: gabrieltool
Platform: UNKNOWN
Classifier: Development Status :: 2 - Pre-Alpha
Classifier: Intended Audience :: Developers
Classifier: License :: OSI Approved :: Apache Software License
Classifier: Natural Language :: English
Classifier: Programming Language :: Python :: 3.5
Classifier: Programming Language :: Python :: 3.6
Classifier: Programming Language :: Python :: 3.7
Requires-Python: >=3.5, <3.8
Requires-Dist: docker
Requires-Dist: fire
Requires-Dist: gabriel-server (==0.1.1)
Requires-Dist: logzero
Requires-Dist: opencv-python (>=3)
Requires-Dist: pip (>=20)
Requires-Dist: setuptools (>=46)
Requires-Dist: tensorflow-serving-api (~=1.15)
